README.md
setup.py
distributions_udacity_jbanayo/Binomialdistribution.py
distributions_udacity_jbanayo/Gaussiandistribution.py
distributions_udacity_jbanayo/Generaldistribution.py
distributions_udacity_jbanayo/__init__.py
distributions_udacity_jbanayo.egg-info/PKG-INFO
distributions_udacity_jbanayo.egg-info/SOURCES.txt
distributions_udacity_jbanayo.egg-info/dependency_links.txt
distributions_udacity_jbanayo.egg-info/not-zip-safe
distributions_udacity_jbanayo.egg-info/top_level.txt