Metadata-Version: 2.1
Name: distributions-udacity-jbanayo
Version: 0.1
Summary: Gaussian distributions
